{
  "namespaces": [
    "public"
  ],
  "name": "public",
  "tables": [
    {
      "columns": {
        "id": {
          "name": "id",
          "type": "text",
          "unsigned": false,
          "autoincrement": false,
          "primary": false,
          "nullable": false,
          "mappedType": "text"
        },
        "movement_type": {
          "name": "movement_type",
          "type": "text",
          "unsigned": false,
          "autoincrement": false,
          "primary": false,
          "nullable": false,
          "enumItems": [
            "supplier_receipt",
            "transfer_out",
            "transfer_in",
            "adjustment",
            "sale",
            "return",
            "damage",
            "theft",
            "expired"
          ],
          "mappedType": "enum"
        },
        "reference_id": {
          "name": "reference_id",
          "type": "text",
          "unsigned": false,
          "autoincrement": false,
          "primary": false,
          "nullable": true,
          "mappedType": "text"
        },
        "reference_type": {
          "name": "reference_type",
          "type": "text",
          "unsigned": false,
          "autoincrement": false,
          "primary": false,
          "nullable": true,
          "mappedType": "text"
        },
        "product_id": {
          "name": "product_id",
          "type": "text",
          "unsigned": false,
          "autoincrement": false,
          "primary": false,
          "nullable": false,
          "mappedType": "text"
        },
        "product_variant_id": {
          "name": "product_variant_id",
          "type": "text",
          "unsigned": false,
          "autoincrement": false,
          "primary": false,
          "nullable": true,
          "mappedType": "text"
        },
        "product_title": {
          "name": "product_title",
          "type": "text",
          "unsigned": false,
          "autoincrement": false,
          "primary": false,
          "nullable": false,
          "mappedType": "text"
        },
        "from_location_id": {
          "name": "from_location_id",
          "type": "text",
          "unsigned": false,
          "autoincrement": false,
          "primary": false,
          "nullable": true,
          "mappedType": "text"
        },
        "from_location_name": {
          "name": "from_location_name",
          "type": "text",
          "unsigned": false,
          "autoincrement": false,
          "primary": false,
          "nullable": true,
          "mappedType": "text"
        },
        "to_location_id": {
          "name": "to_location_id",
          "type": "text",
          "unsigned": false,
          "autoincrement": false,
          "primary": false,
          "nullable": true,
          "mappedType": "text"
        },
        "to_location_name": {
          "name": "to_location_name",
          "type": "text",
          "unsigned": false,
          "autoincrement": false,
          "primary": false,
          "nullable": true,
          "mappedType": "text"
        },
        "quantity": {
          "name": "quantity",
          "type": "integer",
          "unsigned": false,
          "autoincrement": false,
          "primary": false,
          "nullable": false,
          "mappedType": "integer"
        },
        "unit_cost": {
          "name": "unit_cost",
          "type": "integer",
          "unsigned": false,
          "autoincrement": false,
          "primary": false,
          "nullable": true,
          "mappedType": "integer"
        },
        "total_cost": {
          "name": "total_cost",
          "type": "integer",
          "unsigned": false,
          "autoincrement": false,
          "primary": false,
          "nullable": true,
          "mappedType": "integer"
        },
        "reason": {
          "name": "reason",
          "type": "text",
          "unsigned": false,
          "autoincrement": false,
          "primary": false,
          "nullable": true,
          "mappedType": "text"
        },
        "notes": {
          "name": "notes",
          "type": "text",
          "unsigned": false,
          "autoincrement": false,
          "primary": false,
          "nullable": true,
          "mappedType": "text"
        },
        "performed_by": {
          "name": "performed_by",
          "type": "text",
          "unsigned": false,
          "autoincrement": false,
          "primary": false,
          "nullable": true,
          "mappedType": "text"
        },
        "performed_at": {
          "name": "performed_at",
          "type": "timestamptz",
          "unsigned": false,
          "autoincrement": false,
          "primary": false,
          "nullable": false,
          "length": 6,
          "mappedType": "datetime"
        },
        "metadata": {
          "name": "metadata",
          "type": "jsonb",
          "unsigned": false,
          "autoincrement": false,
          "primary": false,
          "nullable": true,
          "mappedType": "json"
        },
        "created_at": {
          "name": "created_at",
          "type": "timestamptz",
          "unsigned": false,
          "autoincrement": false,
          "primary": false,
          "nullable": false,
          "length": 6,
          "default": "now()",
          "mappedType": "datetime"
        },
        "updated_at": {
          "name": "updated_at",
          "type": "timestamptz",
          "unsigned": false,
          "autoincrement": false,
          "primary": false,
          "nullable": false,
          "length": 6,
          "default": "now()",
          "mappedType": "datetime"
        },
        "deleted_at": {
          "name": "deleted_at",
          "type": "timestamptz",
          "unsigned": false,
          "autoincrement": false,
          "primary": false,
          "nullable": true,
          "length": 6,
          "mappedType": "datetime"
        }
      },
      "name": "inventory_movement",
      "schema": "public",
      "indexes": [
        {
          "keyName": "IDX_inventory_movement_deleted_at",
          "columnNames": [],
          "composite": false,
          "constraint": false,
          "primary": false,
          "unique": false,
          "expression": "CREATE INDEX IF NOT EXISTS \"IDX_inventory_movement_deleted_at\" ON \"inventory_movement\" (deleted_at) WHERE deleted_at IS NULL"
        },
        {
          "keyName": "inventory_movement_pkey",
          "columnNames": [
            "id"
          ],
          "composite": false,
          "constraint": true,
          "primary": true,
          "unique": true
        }
      ],
      "checks": [],
      "foreignKeys": {},
      "nativeEnums": {}
    },
    {
      "columns": {
        "id": {
          "name": "id",
          "type": "text",
          "unsigned": false,
          "autoincrement": false,
          "primary": false,
          "nullable": false,
          "mappedType": "text"
        },
        "name": {
          "name": "name",
          "type": "text",
          "unsigned": false,
          "autoincrement": false,
          "primary": false,
          "nullable": false,
          "mappedType": "text"
        },
        "legal_name": {
          "name": "legal_name",
          "type": "text",
          "unsigned": false,
          "autoincrement": false,
          "primary": false,
          "nullable": false,
          "mappedType": "text"
        },
        "code": {
          "name": "code",
          "type": "text",
          "unsigned": false,
          "autoincrement": false,
          "primary": false,
          "nullable": true,
          "mappedType": "text"
        },
        "tax_id": {
          "name": "tax_id",
          "type": "text",
          "unsigned": false,
          "autoincrement": false,
          "primary": false,
          "nullable": false,
          "mappedType": "text"
        },
        "email": {
          "name": "email",
          "type": "text",
          "unsigned": false,
          "autoincrement": false,
          "primary": false,
          "nullable": true,
          "mappedType": "text"
        },
        "phone": {
          "name": "phone",
          "type": "text",
          "unsigned": false,
          "autoincrement": false,
          "primary": false,
          "nullable": true,
          "mappedType": "text"
        },
        "website": {
          "name": "website",
          "type": "text",
          "unsigned": false,
          "autoincrement": false,
          "primary": false,
          "nullable": true,
          "mappedType": "text"
        },
        "address_line_1": {
          "name": "address_line_1",
          "type": "text",
          "unsigned": false,
          "autoincrement": false,
          "primary": false,
          "nullable": true,
          "mappedType": "text"
        },
        "address_line_2": {
          "name": "address_line_2",
          "type": "text",
          "unsigned": false,
          "autoincrement": false,
          "primary": false,
          "nullable": true,
          "mappedType": "text"
        },
        "city": {
          "name": "city",
          "type": "text",
          "unsigned": false,
          "autoincrement": false,
          "primary": false,
          "nullable": true,
          "mappedType": "text"
        },
        "postal_code": {
          "name": "postal_code",
          "type": "text",
          "unsigned": false,
          "autoincrement": false,
          "primary": false,
          "nullable": true,
          "mappedType": "text"
        },
        "province": {
          "name": "province",
          "type": "text",
          "unsigned": false,
          "autoincrement": false,
          "primary": false,
          "nullable": true,
          "mappedType": "text"
        },
        "country_code": {
          "name": "country_code",
          "type": "text",
          "unsigned": false,
          "autoincrement": false,
          "primary": false,
          "nullable": true,
          "mappedType": "text"
        },
        "supplier_type": {
          "name": "supplier_type",
          "type": "text",
          "unsigned": false,
          "autoincrement": false,
          "primary": false,
          "nullable": false,
          "default": "'standard'",
          "mappedType": "text"
        },
        "payment_terms": {
          "name": "payment_terms",
          "type": "text",
          "unsigned": false,
          "autoincrement": false,
          "primary": false,
          "nullable": true,
          "mappedType": "text"
        },
        "currency_code": {
          "name": "currency_code",
          "type": "text",
          "unsigned": false,
          "autoincrement": false,
          "primary": false,
          "nullable": false,
          "default": "'EUR'",
          "mappedType": "text"
        },
        "discount_percentage": {
          "name": "discount_percentage",
          "type": "integer",
          "unsigned": false,
          "autoincrement": false,
          "primary": false,
          "nullable": true,
          "mappedType": "integer"
        },
        "is_active": {
          "name": "is_active",
          "type": "boolean",
          "unsigned": false,
          "autoincrement": false,
          "primary": false,
          "nullable": false,
          "default": "true",
          "mappedType": "boolean"
        },
        "notes": {
          "name": "notes",
          "type": "text",
          "unsigned": false,
          "autoincrement": false,
          "primary": false,
          "nullable": true,
          "mappedType": "text"
        },
        "metadata": {
          "name": "metadata",
          "type": "jsonb",
          "unsigned": false,
          "autoincrement": false,
          "primary": false,
          "nullable": true,
          "mappedType": "json"
        },
        "created_at": {
          "name": "created_at",
          "type": "timestamptz",
          "unsigned": false,
          "autoincrement": false,
          "primary": false,
          "nullable": false,
          "length": 6,
          "default": "now()",
          "mappedType": "datetime"
        },
        "updated_at": {
          "name": "updated_at",
          "type": "timestamptz",
          "unsigned": false,
          "autoincrement": false,
          "primary": false,
          "nullable": false,
          "length": 6,
          "default": "now()",
          "mappedType": "datetime"
        },
        "deleted_at": {
          "name": "deleted_at",
          "type": "timestamptz",
          "unsigned": false,
          "autoincrement": false,
          "primary": false,
          "nullable": true,
          "length": 6,
          "mappedType": "datetime"
        }
      },
      "name": "supplier",
      "schema": "public",
      "indexes": [
        {
          "keyName": "IDX_supplier_code_unique",
          "columnNames": [],
          "composite": false,
          "constraint": false,
          "primary": false,
          "unique": false,
          "expression": "CREATE UNIQUE INDEX IF NOT EXISTS \"IDX_supplier_code_unique\" ON \"supplier\" (code) WHERE deleted_at IS NULL"
        },
        {
          "keyName": "IDX_supplier_tax_id_unique",
          "columnNames": [],
          "composite": false,
          "constraint": false,
          "primary": false,
          "unique": false,
          "expression": "CREATE UNIQUE INDEX IF NOT EXISTS \"IDX_supplier_tax_id_unique\" ON \"supplier\" (tax_id) WHERE deleted_at IS NULL"
        },
        {
          "keyName": "IDX_supplier_deleted_at",
          "columnNames": [],
          "composite": false,
          "constraint": false,
          "primary": false,
          "unique": false,
          "expression": "CREATE INDEX IF NOT EXISTS \"IDX_supplier_deleted_at\" ON \"supplier\" (deleted_at) WHERE deleted_at IS NULL"
        },
        {
          "keyName": "supplier_pkey",
          "columnNames": [
            "id"
          ],
          "composite": false,
          "constraint": true,
          "primary": true,
          "unique": true
        }
      ],
      "checks": [],
      "foreignKeys": {},
      "nativeEnums": {}
    },
    {
      "columns": {
        "id": {
          "name": "id",
          "type": "text",
          "unsigned": false,
          "autoincrement": false,
          "primary": false,
          "nullable": false,
          "mappedType": "text"
        },
        "product_id": {
          "name": "product_id",
          "type": "text",
          "unsigned": false,
          "autoincrement": false,
          "primary": false,
          "nullable": false,
          "mappedType": "text"
        },
        "product_variant_id": {
          "name": "product_variant_id",
          "type": "text",
          "unsigned": false,
          "autoincrement": false,
          "primary": false,
          "nullable": true,
          "mappedType": "text"
        },
        "supplier_id": {
          "name": "supplier_id",
          "type": "text",
          "unsigned": false,
          "autoincrement": false,
          "primary": false,
          "nullable": false,
          "mappedType": "text"
        },
        "supplier_sku": {
          "name": "supplier_sku",
          "type": "text",
          "unsigned": false,
          "autoincrement": false,
          "primary": false,
          "nullable": true,
          "mappedType": "text"
        },
        "supplier_product_name": {
          "name": "supplier_product_name",
          "type": "text",
          "unsigned": false,
          "autoincrement": false,
          "primary": false,
          "nullable": true,
          "mappedType": "text"
        },
        "supplier_description": {
          "name": "supplier_description",
          "type": "text",
          "unsigned": false,
          "autoincrement": false,
          "primary": false,
          "nullable": true,
          "mappedType": "text"
        },
        "cost_price": {
          "name": "cost_price",
          "type": "integer",
          "unsigned": false,
          "autoincrement": false,
          "primary": false,
          "nullable": true,
          "mappedType": "integer"
        },
        "currency_code": {
          "name": "currency_code",
          "type": "text",
          "unsigned": false,
          "autoincrement": false,
          "primary": false,
          "nullable": false,
          "default": "'EUR'",
          "mappedType": "text"
        },
        "minimum_order_quantity": {
          "name": "minimum_order_quantity",
          "type": "integer",
          "unsigned": false,
          "autoincrement": false,
          "primary": false,
          "nullable": false,
          "default": "1",
          "mappedType": "integer"
        },
        "lead_time_days": {
          "name": "lead_time_days",
          "type": "integer",
          "unsigned": false,
          "autoincrement": false,
          "primary": false,
          "nullable": true,
          "mappedType": "integer"
        },
        "price_history": {
          "name": "price_history",
          "type": "jsonb",
          "unsigned": false,
          "autoincrement": false,
          "primary": false,
          "nullable": true,
          "mappedType": "json"
        },
        "is_preferred_supplier": {
          "name": "is_preferred_supplier",
          "type": "boolean",
          "unsigned": false,
          "autoincrement": false,
          "primary": false,
          "nullable": false,
          "default": "false",
          "mappedType": "boolean"
        },
        "is_active": {
          "name": "is_active",
          "type": "boolean",
          "unsigned": false,
          "autoincrement": false,
          "primary": false,
          "nullable": false,
          "default": "true",
          "mappedType": "boolean"
        },
        "is_workshop_consumable": {
          "name": "is_workshop_consumable",
          "type": "boolean",
          "unsigned": false,
          "autoincrement": false,
          "primary": false,
          "nullable": false,
          "default": "false",
          "mappedType": "boolean"
        },
        "exclude_from_storefront": {
          "name": "exclude_from_storefront",
          "type": "boolean",
          "unsigned": false,
          "autoincrement": false,
          "primary": false,
          "nullable": false,
          "default": "false",
          "mappedType": "boolean"
        },
        "workshop_category": {
          "name": "workshop_category",
          "type": "text",
          "unsigned": false,
          "autoincrement": false,
          "primary": false,
          "nullable": true,
          "mappedType": "text"
        },
        "last_purchase_date": {
          "name": "last_purchase_date",
          "type": "timestamptz",
          "unsigned": false,
          "autoincrement": false,
          "primary": false,
          "nullable": true,
          "length": 6,
          "mappedType": "datetime"
        },
        "last_price_update": {
          "name": "last_price_update",
          "type": "timestamptz",
          "unsigned": false,
          "autoincrement": false,
          "primary": false,
          "nullable": true,
          "length": 6,
          "mappedType": "datetime"
        },
        "notes": {
          "name": "notes",
          "type": "text",
          "unsigned": false,
          "autoincrement": false,
          "primary": false,
          "nullable": true,
          "mappedType": "text"
        },
        "metadata": {
          "name": "metadata",
          "type": "jsonb",
          "unsigned": false,
          "autoincrement": false,
          "primary": false,
          "nullable": true,
          "mappedType": "json"
        },
        "created_at": {
          "name": "created_at",
          "type": "timestamptz",
          "unsigned": false,
          "autoincrement": false,
          "primary": false,
          "nullable": false,
          "length": 6,
          "default": "now()",
          "mappedType": "datetime"
        },
        "updated_at": {
          "name": "updated_at",
          "type": "timestamptz",
          "unsigned": false,
          "autoincrement": false,
          "primary": false,
          "nullable": false,
          "length": 6,
          "default": "now()",
          "mappedType": "datetime"
        },
        "deleted_at": {
          "name": "deleted_at",
          "type": "timestamptz",
          "unsigned": false,
          "autoincrement": false,
          "primary": false,
          "nullable": true,
          "length": 6,
          "mappedType": "datetime"
        }
      },
      "name": "product_supplier",
      "schema": "public",
      "indexes": [
        {
          "keyName": "IDX_product_supplier_supplier_id",
          "columnNames": [],
          "composite": false,
          "constraint": false,
          "primary": false,
          "unique": false,
          "expression": "CREATE INDEX IF NOT EXISTS \"IDX_product_supplier_supplier_id\" ON \"product_supplier\" (supplier_id) WHERE deleted_at IS NULL"
        },
        {
          "keyName": "IDX_product_supplier_deleted_at",
          "columnNames": [],
          "composite": false,
          "constraint": false,
          "primary": false,
          "unique": false,
          "expression": "CREATE INDEX IF NOT EXISTS \"IDX_product_supplier_deleted_at\" ON \"product_supplier\" (deleted_at) WHERE deleted_at IS NULL"
        },
        {
          "keyName": "product_supplier_pkey",
          "columnNames": [
            "id"
          ],
          "composite": false,
          "constraint": true,
          "primary": true,
          "unique": true
        }
      ],
      "checks": [],
      "foreignKeys": {
        "product_supplier_supplier_id_foreign": {
          "constraintName": "product_supplier_supplier_id_foreign",
          "columnNames": [
            "supplier_id"
          ],
          "localTableName": "public.product_supplier",
          "referencedColumnNames": [
            "id"
          ],
          "referencedTableName": "public.supplier",
          "updateRule": "cascade"
        }
      },
      "nativeEnums": {}
    },
    {
      "columns": {
        "id": {
          "name": "id",
          "type": "text",
          "unsigned": false,
          "autoincrement": false,
          "primary": false,
          "nullable": false,
          "mappedType": "text"
        },
        "display_id": {
          "name": "display_id",
          "type": "text",
          "unsigned": false,
          "autoincrement": false,
          "primary": false,
          "nullable": false,
          "mappedType": "text"
        },
        "supplier_id": {
          "name": "supplier_id",
          "type": "text",
          "unsigned": false,
          "autoincrement": false,
          "primary": false,
          "nullable": false,
          "mappedType": "text"
        },
        "order_type": {
          "name": "order_type",
          "type": "text",
          "unsigned": false,
          "autoincrement": false,
          "primary": false,
          "nullable": false,
          "default": "'supplier'",
          "mappedType": "text"
        },
        "status": {
          "name": "status",
          "type": "text",
          "unsigned": false,
          "autoincrement": false,
          "primary": false,
          "nullable": false,
          "default": "'draft'",
          "mappedType": "text"
        },
        "order_date": {
          "name": "order_date",
          "type": "timestamptz",
          "unsigned": false,
          "autoincrement": false,
          "primary": false,
          "nullable": false,
          "length": 6,
          "mappedType": "datetime"
        },
        "expected_delivery_date": {
          "name": "expected_delivery_date",
          "type": "timestamptz",
          "unsigned": false,
          "autoincrement": false,
          "primary": false,
          "nullable": true,
          "length": 6,
          "mappedType": "datetime"
        },
        "confirmed_at": {
          "name": "confirmed_at",
          "type": "timestamptz",
          "unsigned": false,
          "autoincrement": false,
          "primary": false,
          "nullable": true,
          "length": 6,
          "mappedType": "datetime"
        },
        "shipped_at": {
          "name": "shipped_at",
          "type": "timestamptz",
          "unsigned": false,
          "autoincrement": false,
          "primary": false,
          "nullable": true,
          "length": 6,
          "mappedType": "datetime"
        },
        "received_at": {
          "name": "received_at",
          "type": "timestamptz",
          "unsigned": false,
          "autoincrement": false,
          "primary": false,
          "nullable": true,
          "length": 6,
          "mappedType": "datetime"
        },
        "currency_code": {
          "name": "currency_code",
          "type": "text",
          "unsigned": false,
          "autoincrement": false,
          "primary": false,
          "nullable": false,
          "default": "'EUR'",
          "mappedType": "text"
        },
        "subtotal": {
          "name": "subtotal",
          "type": "integer",
          "unsigned": false,
          "autoincrement": false,
          "primary": false,
          "nullable": false,
          "default": "0",
          "mappedType": "integer"
        },
        "tax_total": {
          "name": "tax_total",
          "type": "integer",
          "unsigned": false,
          "autoincrement": false,
          "primary": false,
          "nullable": false,
          "default": "0",
          "mappedType": "integer"
        },
        "discount_total": {
          "name": "discount_total",
          "type": "integer",
          "unsigned": false,
          "autoincrement": false,
          "primary": false,
          "nullable": false,
          "default": "0",
          "mappedType": "integer"
        },
        "total": {
          "name": "total",
          "type": "integer",
          "unsigned": false,
          "autoincrement": false,
          "primary": false,
          "nullable": false,
          "default": "0",
          "mappedType": "integer"
        },
        "destination_location_id": {
          "name": "destination_location_id",
          "type": "text",
          "unsigned": false,
          "autoincrement": false,
          "primary": false,
          "nullable": true,
          "mappedType": "text"
        },
        "destination_location_name": {
          "name": "destination_location_name",
          "type": "text",
          "unsigned": false,
          "autoincrement": false,
          "primary": false,
          "nullable": true,
          "mappedType": "text"
        },
        "source_location_id": {
          "name": "source_location_id",
          "type": "text",
          "unsigned": false,
          "autoincrement": false,
          "primary": false,
          "nullable": true,
          "mappedType": "text"
        },
        "source_location_name": {
          "name": "source_location_name",
          "type": "text",
          "unsigned": false,
          "autoincrement": false,
          "primary": false,
          "nullable": true,
          "mappedType": "text"
        },
        "reference": {
          "name": "reference",
          "type": "text",
          "unsigned": false,
          "autoincrement": false,
          "primary": false,
          "nullable": true,
          "mappedType": "text"
        },
        "notes": {
          "name": "notes",
          "type": "text",
          "unsigned": false,
          "autoincrement": false,
          "primary": false,
          "nullable": true,
          "mappedType": "text"
        },
        "internal_notes": {
          "name": "internal_notes",
          "type": "text",
          "unsigned": false,
          "autoincrement": false,
          "primary": false,
          "nullable": true,
          "mappedType": "text"
        },
        "created_by": {
          "name": "created_by",
          "type": "text",
          "unsigned": false,
          "autoincrement": false,
          "primary": false,
          "nullable": true,
          "mappedType": "text"
        },
        "received_by": {
          "name": "received_by",
          "type": "text",
          "unsigned": false,
          "autoincrement": false,
          "primary": false,
          "nullable": true,
          "mappedType": "text"
        },
        "metadata": {
          "name": "metadata",
          "type": "jsonb",
          "unsigned": false,
          "autoincrement": false,
          "primary": false,
          "nullable": true,
          "mappedType": "json"
        },
        "created_at": {
          "name": "created_at",
          "type": "timestamptz",
          "unsigned": false,
          "autoincrement": false,
          "primary": false,
          "nullable": false,
          "length": 6,
          "default": "now()",
          "mappedType": "datetime"
        },
        "updated_at": {
          "name": "updated_at",
          "type": "timestamptz",
          "unsigned": false,
          "autoincrement": false,
          "primary": false,
          "nullable": false,
          "length": 6,
          "default": "now()",
          "mappedType": "datetime"
        },
        "deleted_at": {
          "name": "deleted_at",
          "type": "timestamptz",
          "unsigned": false,
          "autoincrement": false,
          "primary": false,
          "nullable": true,
          "length": 6,
          "mappedType": "datetime"
        }
      },
      "name": "supplier_order",
      "schema": "public",
      "indexes": [
        {
          "keyName": "IDX_supplier_order_display_id_unique",
          "columnNames": [],
          "composite": false,
          "constraint": false,
          "primary": false,
          "unique": false,
          "expression": "CREATE UNIQUE INDEX IF NOT EXISTS \"IDX_supplier_order_display_id_unique\" ON \"supplier_order\" (display_id) WHERE deleted_at IS NULL"
        },
        {
          "keyName": "IDX_supplier_order_supplier_id",
          "columnNames": [],
          "composite": false,
          "constraint": false,
          "primary": false,
          "unique": false,
          "expression": "CREATE INDEX IF NOT EXISTS \"IDX_supplier_order_supplier_id\" ON \"supplier_order\" (supplier_id) WHERE deleted_at IS NULL"
        },
        {
          "keyName": "IDX_supplier_order_deleted_at",
          "columnNames": [],
          "composite": false,
          "constraint": false,
          "primary": false,
          "unique": false,
          "expression": "CREATE INDEX IF NOT EXISTS \"IDX_supplier_order_deleted_at\" ON \"supplier_order\" (deleted_at) WHERE deleted_at IS NULL"
        },
        {
          "keyName": "supplier_order_pkey",
          "columnNames": [
            "id"
          ],
          "composite": false,
          "constraint": true,
          "primary": true,
          "unique": true
        }
      ],
      "checks": [],
      "foreignKeys": {
        "supplier_order_supplier_id_foreign": {
          "constraintName": "supplier_order_supplier_id_foreign",
          "columnNames": [
            "supplier_id"
          ],
          "localTableName": "public.supplier_order",
          "referencedColumnNames": [
            "id"
          ],
          "referencedTableName": "public.supplier",
          "updateRule": "cascade"
        }
      },
      "nativeEnums": {}
    },
    {
      "columns": {
        "id": {
          "name": "id",
          "type": "text",
          "unsigned": false,
          "autoincrement": false,
          "primary": false,
          "nullable": false,
          "mappedType": "text"
        },
        "supplier_order_id": {
          "name": "supplier_order_id",
          "type": "text",
          "unsigned": false,
          "autoincrement": false,
          "primary": false,
          "nullable": false,
          "mappedType": "text"
        },
        "product_id": {
          "name": "product_id",
          "type": "text",
          "unsigned": false,
          "autoincrement": false,
          "primary": false,
          "nullable": true,
          "mappedType": "text"
        },
        "product_variant_id": {
          "name": "product_variant_id",
          "type": "text",
          "unsigned": false,
          "autoincrement": false,
          "primary": false,
          "nullable": true,
          "mappedType": "text"
        },
        "product_title": {
          "name": "product_title",
          "type": "text",
          "unsigned": false,
          "autoincrement": false,
          "primary": false,
          "nullable": false,
          "mappedType": "text"
        },
        "product_description": {
          "name": "product_description",
          "type": "text",
          "unsigned": false,
          "autoincrement": false,
          "primary": false,
          "nullable": true,
          "mappedType": "text"
        },
        "product_thumbnail": {
          "name": "product_thumbnail",
          "type": "text",
          "unsigned": false,
          "autoincrement": false,
          "primary": false,
          "nullable": true,
          "mappedType": "text"
        },
        "supplier_sku": {
          "name": "supplier_sku",
          "type": "text",
          "unsigned": false,
          "autoincrement": false,
          "primary": false,
          "nullable": true,
          "mappedType": "text"
        },
        "supplier_product_name": {
          "name": "supplier_product_name",
          "type": "text",
          "unsigned": false,
          "autoincrement": false,
          "primary": false,
          "nullable": true,
          "mappedType": "text"
        },
        "quantity_ordered": {
          "name": "quantity_ordered",
          "type": "integer",
          "unsigned": false,
          "autoincrement": false,
          "primary": false,
          "nullable": false,
          "mappedType": "integer"
        },
        "quantity_received": {
          "name": "quantity_received",
          "type": "integer",
          "unsigned": false,
          "autoincrement": false,
          "primary": false,
          "nullable": false,
          "default": "0",
          "mappedType": "integer"
        },
        "quantity_pending": {
          "name": "quantity_pending",
          "type": "integer",
          "unsigned": false,
          "autoincrement": false,
          "primary": false,
          "nullable": false,
          "default": "0",
          "mappedType": "integer"
        },
        "unit_price": {
          "name": "unit_price",
          "type": "integer",
          "unsigned": false,
          "autoincrement": false,
          "primary": false,
          "nullable": false,
          "mappedType": "integer"
        },
        "tax_rate": {
          "name": "tax_rate",
          "type": "integer",
          "unsigned": false,
          "autoincrement": false,
          "primary": false,
          "nullable": false,
          "default": "0",
          "mappedType": "integer"
        },
        "discount_rate": {
          "name": "discount_rate",
          "type": "integer",
          "unsigned": false,
          "autoincrement": false,
          "primary": false,
          "nullable": false,
          "default": "0",
          "mappedType": "integer"
        },
        "total_price": {
          "name": "total_price",
          "type": "integer",
          "unsigned": false,
          "autoincrement": false,
          "primary": false,
          "nullable": false,
          "mappedType": "integer"
        },
        "received_at": {
          "name": "received_at",
          "type": "timestamptz",
          "unsigned": false,
          "autoincrement": false,
          "primary": false,
          "nullable": true,
          "length": 6,
          "mappedType": "datetime"
        },
        "received_by": {
          "name": "received_by",
          "type": "text",
          "unsigned": false,
          "autoincrement": false,
          "primary": false,
          "nullable": true,
          "mappedType": "text"
        },
        "reception_notes": {
          "name": "reception_notes",
          "type": "text",
          "unsigned": false,
          "autoincrement": false,
          "primary": false,
          "nullable": true,
          "mappedType": "text"
        },
        "line_status": {
          "name": "line_status",
          "type": "text",
          "unsigned": false,
          "autoincrement": false,
          "primary": false,
          "nullable": false,
          "default": "'pending'",
          "enumItems": [
            "pending",
            "partial",
            "received",
            "incident",
            "cancelled"
          ],
          "mappedType": "enum"
        },
        "notes": {
          "name": "notes",
          "type": "text",
          "unsigned": false,
          "autoincrement": false,
          "primary": false,
          "nullable": true,
          "mappedType": "text"
        },
        "metadata": {
          "name": "metadata",
          "type": "jsonb",
          "unsigned": false,
          "autoincrement": false,
          "primary": false,
          "nullable": true,
          "mappedType": "json"
        },
        "created_at": {
          "name": "created_at",
          "type": "timestamptz",
          "unsigned": false,
          "autoincrement": false,
          "primary": false,
          "nullable": false,
          "length": 6,
          "default": "now()",
          "mappedType": "datetime"
        },
        "updated_at": {
          "name": "updated_at",
          "type": "timestamptz",
          "unsigned": false,
          "autoincrement": false,
          "primary": false,
          "nullable": false,
          "length": 6,
          "default": "now()",
          "mappedType": "datetime"
        },
        "deleted_at": {
          "name": "deleted_at",
          "type": "timestamptz",
          "unsigned": false,
          "autoincrement": false,
          "primary": false,
          "nullable": true,
          "length": 6,
          "mappedType": "datetime"
        }
      },
      "name": "supplier_order_line",
      "schema": "public",
      "indexes": [
        {
          "keyName": "IDX_supplier_order_line_supplier_order_id",
          "columnNames": [],
          "composite": false,
          "constraint": false,
          "primary": false,
          "unique": false,
          "expression": "CREATE INDEX IF NOT EXISTS \"IDX_supplier_order_line_supplier_order_id\" ON \"supplier_order_line\" (supplier_order_id) WHERE deleted_at IS NULL"
        },
        {
          "keyName": "IDX_supplier_order_line_deleted_at",
          "columnNames": [],
          "composite": false,
          "constraint": false,
          "primary": false,
          "unique": false,
          "expression": "CREATE INDEX IF NOT EXISTS \"IDX_supplier_order_line_deleted_at\" ON \"supplier_order_line\" (deleted_at) WHERE deleted_at IS NULL"
        },
        {
          "keyName": "supplier_order_line_pkey",
          "columnNames": [
            "id"
          ],
          "composite": false,
          "constraint": true,
          "primary": true,
          "unique": true
        }
      ],
      "checks": [],
      "foreignKeys": {
        "supplier_order_line_supplier_order_id_foreign": {
          "constraintName": "supplier_order_line_supplier_order_id_foreign",
          "columnNames": [
            "supplier_order_id"
          ],
          "localTableName": "public.supplier_order_line",
          "referencedColumnNames": [
            "id"
          ],
          "referencedTableName": "public.supplier_order",
          "updateRule": "cascade"
        }
      },
      "nativeEnums": {}
    }
  ],
  "nativeEnums": {}
}
